<?xml version="1.0" encoding="UTF-8"?>
<!-- edited with XMLSPY v2004 rel. 2 U (http://www.xmlspy.com) by imc (imc) -->
<BadWords>
	<Word Msg="cock"/>
	<Word Msg="ｃｏｃｋ"/>
	<Word Msg="cunt"/>
	<Word Msg="suck"/>
	<Word Msg="ｓｕｃｋ"/>
	<Word Msg="damn"/>
	<Word Msg="ｄａｍｎ"/>
	<Word Msg="dick"/>
	<Word Msg="ｄｉｃｋ"/>
	<Word Msg="dildo"/>
	<Word Msg="pussy"/>
	<Word Msg="ｐｕｓｓｙ"/>
	<Word Msg="slave"/>
	<Word Msg="swap"/>
	<Word Msg="whore"/>
	<Word Msg="asshole"/>
	<Word Msg="愛液"/>
	<Word Msg="アナル"/>
	<Word Msg="ｱﾅﾙ"/>
	<Word Msg="ana|"/>
	<Word Msg="anal"/>
	<Word Msg="anar"/>
	<Word Msg="anaru"/>
	<Word Msg="あぬす"/>
	<Word Msg="アヌス"/>
	<Word Msg="ｱﾇｽ"/>
	<Word Msg="陰核"/>
	<Word Msg="陰茎"/>
	<Word Msg="陰唇"/>
	<Word Msg="淫売"/>
	<Word Msg="淫乱"/>
	<Word Msg="ヴァギナ"/>
	<Word Msg="ヴぁぎな"/>
	<Word Msg="ｳﾞｧｷﾞﾅ"/>
	<Word Msg="vagina"/>
	<Word Msg="オナニ"/>
	<Word Msg="おなに"/>
	<Word Msg="ｵﾅﾆ"/>
	<Word Msg="おなに-"/>
	<Word Msg="おなにー"/>
	<Word Msg="おなに一"/>
	<Word Msg="オナ二"/>
	<Word Msg="onani"/>
	<Word Msg="onani-"/>
	<Word Msg="onanii"/>
	<Word Msg="おまんこ"/>
	<Word Msg="ｵﾏﾝｺ"/>
	<Word Msg="オマンコ"/>
	<Word Msg="亀頭"/>
	<Word Msg="クリトリス"/>
	<Word Msg="クリトりス"/>
	<Word Msg="クりトリス"/>
	<Word Msg="クりトりス"/>
	<Word Msg="くリとリす"/>
	<Word Msg="くリとりす"/>
	<Word Msg="くりとリす"/>
	<Word Msg="くりとりす"/>
	<Word Msg="ｸﾘﾄﾘｽ"/>
	<Word Msg="clitoris"/>
	<Word Msg="kulitolisu"/>
	<Word Msg="kulitorisu"/>
	<Word Msg="kuritolisu"/>
	<Word Msg="kuritorisu"/>
	<Word Msg="強姦"/>
	<Word Msg="ザーメン"/>
	<Word Msg="ざーめん"/>
	<Word Msg="ザ-メン"/>
	<Word Msg="ざ-めん"/>
	<Word Msg="ザ一メン"/>
	<Word Msg="ざ一めん"/>
	<Word Msg="zaamen"/>
	<Word Msg="za-men"/>
	<Word Msg="自慰"/>
	<Word Msg="シックスナイン"/>
	<Word Msg="しっくすないん"/>
	<Word Msg="ｼｯｸｽﾅｲﾝ"/>
	<Word Msg="射精"/>
	<Word Msg="手淫"/>
	<Word Msg="女性器"/>
	<Word Msg="精液"/>
	<Word Msg="性交"/>
	<Word Msg="セックス"/>
	<Word Msg="せっくす"/>
	<Word Msg="ｾｯｸｽ"/>
	<Word Msg="sekkusu"/>
	<Word Msg="sex"/>
	<Word Msg="ｓｅｘ"/>
	<Word Msg="s-e-x"/>
	<Word Msg="前戯"/>
	<Word Msg="ぜんぎ"/>
	<Word Msg="センズリ"/>
	<Word Msg="せんずり"/>
	<Word Msg="sennzuli"/>
	<Word Msg="sennzuri"/>
	<Word Msg="senzuli"/>
	<Word Msg="senzuri"/>
	<Word Msg="男根"/>
	<Word Msg="男性器"/>
	<Word Msg="膣"/>
	<Word Msg="チャH"/>
	<Word Msg="珍こ"/>
	<Word Msg="珍コ"/>
	<Word Msg="珍ｺ"/>
	<Word Msg="チンコ"/>
	<Word Msg="ちんこ"/>
	<Word Msg="ﾁﾝｺ"/>
	<Word Msg="chinco"/>
	<Word Msg="chinko"/>
	<Word Msg="ｃｈｉｎｋｏ"/>
	<Word Msg="chinnco"/>
	<Word Msg="chinnko"/>
	<Word Msg="tinco"/>
	<Word Msg="tinko"/>
	<Word Msg="tinnco"/>
	<Word Msg="tinnko"/>
	<Word Msg="珍ぽ"/>
	<Word Msg="珍ポ"/>
	<Word Msg="珍ﾎﾟ"/>
	<Word Msg="チンポ"/>
	<Word Msg="ちんぽ"/>
	<Word Msg="ﾁﾝﾎﾟ"/>
	<Word Msg="chinnpo"/>
	<Word Msg="chinpo"/>
	<Word Msg="ｃｈｉｎｐｏ"/>
	<Word Msg="tinnpo"/>
	<Word Msg="tinpo"/>
	<Word Msg="肉棒"/>
	<Word Msg="売女"/>
	<Word Msg="ばぁぎな"/>
	<Word Msg="バァギナ"/>
	<Word Msg="ﾊﾞｧｷﾞﾅ"/>
	<Word Msg="ばぎな"/>
	<Word Msg="バギナ"/>
	<Word Msg="ぶぁぎな"/>
	<Word Msg="bagina"/>
	<Word Msg="ふぁっく"/>
	<Word Msg="ファック"/>
	<Word Msg="fuck"/>
	<Word Msg="ｆｕｃｋ"/>
	<Word Msg="ふぇらちお"/>
	<Word Msg="フェラチオ"/>
	<Word Msg="ﾌｪﾗﾁｵ"/>
	<Word Msg="felachio"/>
	<Word Msg="felatio"/>
	<Word Msg="fellachio"/>
	<Word Msg="fellatio"/>
	<Word Msg="ferachio"/>
	<Word Msg="feratio"/>
	<Word Msg="ペニス"/>
	<Word Msg="ぺにす"/>
	<Word Msg="ﾍﾟﾆｽ"/>
	<Word Msg="ペ二ス"/>
	<Word Msg="penis"/>
	<Word Msg="勃起"/>
	<Word Msg="ぼっき"/>
	<Word Msg="bokki"/>
	<Word Msg="ﾏｿｺ"/>
	<Word Msg="マソコ"/>
	<Word Msg="マンコ"/>
	<Word Msg="まんこ"/>
	<Word Msg="ﾏﾝｺ"/>
	<Word Msg="まんコ"/>
	<Word Msg="manco"/>
	<Word Msg="manko"/>
	<Word Msg="ｍａｎｋｏ"/>
	<Word Msg="mannco"/>
	<Word Msg="mannko"/>
	<Word Msg="牝奴隷"/>
	<Word Msg="めすどれい"/>
	<Word Msg="メスドレイ"/>
	<Word Msg="mesudorei"/>
	<Word Msg="性奴隷"/>
	<Word Msg="せいどれい"/>
	<Word Msg="セイドレイ"/>
	<Word Msg="seidorei"/>
	<Word Msg="やりまん"/>
	<Word Msg="ヤリマン"/>
	<Word Msg="ﾔﾘﾏﾝ"/>
	<Word Msg="輪姦"/>
	<Word Msg="レイプ"/>
	<Word Msg="れいぷ"/>
	<Word Msg="ﾚｲﾌﾟ"/>
	<Word Msg="rape"/>
	<Word Msg="reipu"/>
	<Word Msg="{nl}"/>
	<Word Msg="ねくそん"/>
	<Word Msg="おちんちん"/>
</BadWords>
